pytonika/__init__.py
pytonika/__version__.py
pytonika/_client.py
pytonika/devices/__init__.py
pytonika/devices/access_points/__init__.py
pytonika/devices/access_points/access_point.py
pytonika/devices/gateways/__init__.py
pytonika/devices/gateways/gateway.py
pytonika/devices/routers/__init__.py
pytonika/devices/routers/router.py
pytonika/devices/routers/rut200.py
pytonika/devices/routers/rut240.py
pytonika/devices/routers/rut241.py
pytonika/devices/routers/rut956.py
pytonika/devices/routers/rutx08.py
pytonika/devices/routers/rutx50.py
pytonika/devices/switches/__init__.py
pytonika/devices/switches/switch.py
pytonika/endpoints/__init__.py
pytonika/endpoints/authentication.py
pytonika/endpoints/firewall.py
pytonika/endpoints/firmware.py
pytonika/endpoints/interfaces.py
pytonika/endpoints/unauthorized.py
pytonika/endpoints/users.py
pytonika/endpoints/wireguard.py
pytonika-0.2.0.dist-info/licenses/LICENSE
pytonika-0.2.0.dist-info/METADATA
pytonika-0.2.0.dist-info/WHEEL
pytonika-0.2.0.dist-info/top_level.txt
pytonika-0.2.0.dist-info/RECORD
