Metadata-Version: 2.4
Name: pytonika
Version: 0.2.0
Summary: Python wrapper for the Teltonika API.
Author-email: Iker García Calviño <iker.gcalvino@udc.es>
License: MIT License
Project-URL: Homepage, https://github.com/ikergcalvino/pytonika
Project-URL: Repository, https://github.com/ikergcalvino/pytonika.git
Project-URL: Issues, https://github.com/ikergcalvino/pytonika/issues
Keywords: teltonika,api,python,networking,routers,gateways,access-points,switches
Classifier: Development Status :: 3 - Alpha
Classifier: Intended Audience :: Developers
Classifier: Intended Audience :: System Administrators
Classifier: Topic :: Software Development :: Libraries :: Python Modules
Classifier: Topic :: System :: Networking
Classifier: Topic :: Communications
Classifier: License :: OSI Approved :: MIT License
Classifier: Programming Language :: Python :: 3
Classifier: Programming Language :: Python :: 3.10
Classifier: Programming Language :: Python :: 3.11
Classifier: Programming Language :: Python :: 3.12
Classifier: Programming Language :: Python :: 3.13
Requires-Python: >=3.10
License-File: LICENSE
Requires-Dist: httpx>=0.28.1
Dynamic: license-file
